{
    "os": "Linux-5.15.0-88-generic-x86_64-with-glibc2.35",
    "python": "3.10.14",
    "heartbeatAt": "2024-05-14T08:49:41.821892",
    "startedAt": "2024-05-14T08:49:41.084408",
    "docker": null,
    "cuda": null,
    "args": [],
    "state": "running",
    "program": "/home/usuaris/imatge/joan.manel.cardenas/age_predictions/main.py",
    "codePathLocal": "main.py",
    "codePath": "main.py",
    "git": {
        "remote": "git@github.com:manelcardenas/age_predictions.git",
        "commit": "b6f5dbe1fd5d7c0f4ada50a7e70312fda620a62f"
    },
    "email": "joan.manel.cardenas@estudiantat.upc.edu",
    "root": "/home/usuaris/imatge/joan.manel.cardenas/age_predictions",
    "host": "gpic14",
    "username": "joan.manel.cardenas",
    "executable": "/home/usuaris/imatge/joan.manel.cardenas/.conda/envs/Brain_age2/bin/python3",
    "cpu_count": 20,
    "cpu_count_logical": 40,
    "cpu_freq": {
        "current": 1802.2733249999997,
        "min": 1000.0,
        "max": 3200.0
    },
    "cpu_freq_per_core": [
        {
            "current": 2900.001,
            "min": 1000.0,
            "max": 3200.0
        },
        {
            "current": 2900.001,
            "min": 1000.0,
            "max": 3200.0
        },
        {
            "current": 1864.049,
            "min": 1000.0,
            "max": 3200.0
        },
        {
            "current": 1862.536,
            "min": 1000.0,
            "max": 3200.0
        },
        {
            "current": 2500.0,
            "min": 1000.0,
            "max": 3200.0
        },
        {
            "current": 2659.914,
            "min": 1000.0,
            "max": 3200.0
        },
        {
            "current": 2900.002,
            "min": 1000.0,
            "max": 3200.0
        },
        {
            "current": 1000.0,
            "min": 1000.0,
            "max": 3200.0
        },
        {
            "current": 3200.0,
            "min": 1000.0,
            "max": 3200.0
        },
        {
            "current": 1100.0,
            "min": 1000.0,
            "max": 3200.0
        },
        {
            "current": 3200.0,
            "min": 1000.0,
            "max": 3200.0
        },
        {
            "current": 1000.0,
            "min": 1000.0,
            "max": 3200.0
        },
        {
            "current": 1000.0,
            "min": 1000.0,
            "max": 3200.0
        },
        {
            "current": 2900.0,
            "min": 1000.0,
            "max": 3200.0
        },
        {
            "current": 1000.0,
            "min": 1000.0,
            "max": 3200.0
        },
        {
            "current": 1000.0,
            "min": 1000.0,
            "max": 3200.0
        },
        {
            "current": 1000.0,
            "min": 1000.0,
            "max": 3200.0
        },
        {
            "current": 1000.0,
            "min": 1000.0,
            "max": 3200.0
        },
        {
            "current": 1000.0,
            "min": 1000.0,
            "max": 3200.0
        },
        {
            "current": 1000.0,
            "min": 1000.0,
            "max": 3200.0
        },
        {
            "current": 2899.998,
            "min": 1000.0,
            "max": 3200.0
        },
        {
            "current": 2899.999,
            "min": 1000.0,
            "max": 3200.0
        },
        {
            "current": 1882.371,
            "min": 1000.0,
            "max": 3200.0
        },
        {
            "current": 1000.0,
            "min": 1000.0,
            "max": 3200.0
        },
        {
            "current": 3200.0,
            "min": 1000.0,
            "max": 3200.0
        },
        {
            "current": 2622.062,
            "min": 1000.0,
            "max": 3200.0
        },
        {
            "current": 1000.0,
            "min": 1000.0,
            "max": 3200.0
        },
        {
            "current": 1000.0,
            "min": 1000.0,
            "max": 3200.0
        },
        {
            "current": 1000.0,
            "min": 1000.0,
            "max": 3200.0
        },
        {
            "current": 1000.0,
            "min": 1000.0,
            "max": 3200.0
        },
        {
            "current": 1000.0,
            "min": 1000.0,
            "max": 3200.0
        },
        {
            "current": 1000.0,
            "min": 1000.0,
            "max": 3200.0
        },
        {
            "current": 1000.0,
            "min": 1000.0,
            "max": 3200.0
        },
        {
            "current": 1000.0,
            "min": 1000.0,
            "max": 3200.0
        },
        {
            "current": 3200.0,
            "min": 1000.0,
            "max": 3200.0
        },
        {
            "current": 1000.0,
            "min": 1000.0,
            "max": 3200.0
        },
        {
            "current": 3200.0,
            "min": 1000.0,
            "max": 3200.0
        },
        {
            "current": 1000.0,
            "min": 1000.0,
            "max": 3200.0
        },
        {
            "current": 1000.0,
            "min": 1000.0,
            "max": 3200.0
        },
        {
            "current": 1000.0,
            "min": 1000.0,
            "max": 3200.0
        }
    ],
    "disk": {
        "/": {
            "total": 97.87200164794922,
            "used": 24.34423065185547
        }
    },
    "gpu": "NVIDIA GeForce RTX 3090",
    "gpu_count": 3,
    "gpu_devices": [
        {
            "name": "NVIDIA GeForce RTX 3090",
            "memory_total": 25769803776
        },
        {
            "name": "NVIDIA GeForce RTX 3090",
            "memory_total": 25769803776
        },
        {
            "name": "NVIDIA GeForce RTX 3090",
            "memory_total": 25769803776
        }
    ],
    "memory": {
        "total": 251.54028701782227
    }
}
